Metadata-Version: 2.1
Name: cmsplugin-gallery
Version: 2.0.3
Summary: DjangoCMS image gallery plugin with drag&drop reordering in admin, support for thumbnails and jQueryTOOLS overlay.
Home-page: https://github.com/piotrkilczuk/cmsplugin_gallery
Author: Piotr Kilczuk
Author-email: piotr@tymaszweb.pl
License: UNKNOWN
Platform: UNKNOWN
Provides: cmsplugin_gallery
Requires-Python: >=3.7
License-File: LICENSE
License-File: AUTHORS
Requires-Dist: django-cms (>=3.9.0)
Requires-Dist: django-inline-ordering (==1.0.2)
Requires-Dist: easy-thumbnails
Requires-Dist: django-filer
